susytester/__init__.py
susytester/__main__.py
susytester/cli.py
susytester/download.py
susytester/logger.py
susytester/prettylogger.py
susytester/test.py
susy_tester-0.0.1.post1.dist-info/LICENSE
susy_tester-0.0.1.post1.dist-info/METADATA
susy_tester-0.0.1.post1.dist-info/WHEEL
susy_tester-0.0.1.post1.dist-info/top_level.txt
susy_tester-0.0.1.post1.dist-info/RECORD
