Metadata-Version: 2.1
Name: susy-tester
Version: 0.0.1.post1
Summary: Testador de soluções para o SuSy da UNICAMP
Home-page: https://www.github.com/serramatutu/susy-tester
Author: Lucas Valente
Author-email: lucasvvop@hotmail.com
License: MIT
Platform: UNKNOWN
Classifier: Programming Language :: Python :: 3
Classifier: License :: OSI Approved :: MIT License
Classifier: Operating System :: OS Independent
Requires-Dist: termcolor
Requires-Dist: requests
